{
	"configurations" : 
	[
		{
			"directories" : 
			[
				{
					"build" : ".",
					"childIndexes" : 
					[
						1,
						4
					],
					"hasInstallRule" : true,
					"jsonFile" : "directory-.-Debug-f5ebdc15457944623624.json",
					"minimumCMakeVersion" : 
					{
						"string" : "3.23"
					},
					"projectIndex" : 0,
					"source" : ".",
					"targetIndexes" : 
					[
						0
					]
				},
				{
					"build" : "_deps/googletest-build",
					"childIndexes" : 
					[
						2
					],
					"hasInstallRule" : true,
					"jsonFile" : "directory-_deps.googletest-build-Debug-fa1b18db30f420365ea4.json",
					"minimumCMakeVersion" : 
					{
						"string" : "3.5"
					},
					"parentIndex" : 0,
					"projectIndex" : 1,
					"source" : "cmake-build-debug/_deps/googletest-src"
				},
				{
					"build" : "_deps/googletest-build/googlemock",
					"childIndexes" : 
					[
						3
					],
					"hasInstallRule" : true,
					"jsonFile" : "directory-_deps.googletest-build.googlemock-Debug-97eb8eab7e56a33455a7.json",
					"minimumCMakeVersion" : 
					{
						"string" : "3.5"
					},
					"parentIndex" : 1,
					"projectIndex" : 2,
					"source" : "cmake-build-debug/_deps/googletest-src/googlemock",
					"targetIndexes" : 
					[
						2,
						3
					]
				},
				{
					"build" : "_deps/googletest-build/googletest",
					"hasInstallRule" : true,
					"jsonFile" : "directory-_deps.googletest-build.googletest-Debug-963bc627bc062e6a2666.json",
					"minimumCMakeVersion" : 
					{
						"string" : "3.5"
					},
					"parentIndex" : 2,
					"projectIndex" : 3,
					"source" : "cmake-build-debug/_deps/googletest-src/googletest",
					"targetIndexes" : 
					[
						4,
						5
					]
				},
				{
					"build" : "BigInt_dir",
					"jsonFile" : "directory-BigInt_dir-Debug-81f4d89234378d4e6b3f.json",
					"minimumCMakeVersion" : 
					{
						"string" : "3.23"
					},
					"parentIndex" : 0,
					"projectIndex" : 0,
					"source" : "BigInt_dir",
					"targetIndexes" : 
					[
						1
					]
				}
			],
			"name" : "Debug",
			"projects" : 
			[
				{
					"childIndexes" : 
					[
						1
					],
					"directoryIndexes" : 
					[
						0,
						4
					],
					"name" : "BigInt",
					"targetIndexes" : 
					[
						0,
						1
					]
				},
				{
					"childIndexes" : 
					[
						2
					],
					"directoryIndexes" : 
					[
						1
					],
					"name" : "googletest-distribution",
					"parentIndex" : 0
				},
				{
					"childIndexes" : 
					[
						3
					],
					"directoryIndexes" : 
					[
						2
					],
					"name" : "gmock",
					"parentIndex" : 1,
					"targetIndexes" : 
					[
						2,
						3
					]
				},
				{
					"directoryIndexes" : 
					[
						3
					],
					"name" : "gtest",
					"parentIndex" : 2,
					"targetIndexes" : 
					[
						4,
						5
					]
				}
			],
			"targets" : 
			[
				{
					"directoryIndex" : 0,
					"id" : "BigInt::@6890427a1f51a3e7e1df",
					"jsonFile" : "target-BigInt-Debug-a4c7b28cff4260f60443.json",
					"name" : "BigInt",
					"projectIndex" : 0
				},
				{
					"directoryIndex" : 4,
					"id" : "BigInt_lib::@569bd4ab7deba7756105",
					"jsonFile" : "target-BigInt_lib-Debug-16c1860818ea33e38e82.json",
					"name" : "BigInt_lib",
					"projectIndex" : 0
				},
				{
					"directoryIndex" : 2,
					"id" : "gmock::@0f7bb11d64f3678238c7",
					"jsonFile" : "target-gmock-Debug-0f5f23f198b4378e48d5.json",
					"name" : "gmock",
					"projectIndex" : 2
				},
				{
					"directoryIndex" : 2,
					"id" : "gmock_main::@0f7bb11d64f3678238c7",
					"jsonFile" : "target-gmock_main-Debug-92c0003e568ebe93a9b1.json",
					"name" : "gmock_main",
					"projectIndex" : 2
				},
				{
					"directoryIndex" : 3,
					"id" : "gtest::@1ea2dfc0605fe3ab2a3f",
					"jsonFile" : "target-gtest-Debug-5d6e4e86f879a92a70b2.json",
					"name" : "gtest",
					"projectIndex" : 3
				},
				{
					"directoryIndex" : 3,
					"id" : "gtest_main::@1ea2dfc0605fe3ab2a3f",
					"jsonFile" : "target-gtest_main-Debug-e7f28f2eba308de3ecc2.json",
					"name" : "gtest_main",
					"projectIndex" : 3
				}
			]
		}
	],
	"kind" : "codemodel",
	"paths" : 
	{
		"build" : "/Users/mac/Desktop/GitHub/NSU-OOP-Cpp/BigInt/cmake-build-debug",
		"source" : "/Users/mac/Desktop/GitHub/NSU-OOP-Cpp/BigInt"
	},
	"version" : 
	{
		"major" : 2,
		"minor" : 4
	}
}
